__init__.py
baostock_data_source.py
data_source_interface.py
utils.py
formatting/__init__.py
formatting/markdown_formatter.py
mseep_a_share_mcp-0.1.1.dist-info/licenses/LICENSE
tools/__init__.py
tools/analysis.py
tools/base.py
tools/date_utils.py
tools/financial_reports.py
tools/indices.py
tools/macroeconomic.py
tools/market_overview.py
tools/stock_market.py
mseep_a_share_mcp-0.1.1.dist-info/METADATA
mseep_a_share_mcp-0.1.1.dist-info/WHEEL
mseep_a_share_mcp-0.1.1.dist-info/top_level.txt
mseep_a_share_mcp-0.1.1.dist-info/RECORD
