Metadata-Version: 2.4
Name: mseep-a-share-mcp
Version: 0.1.1
Summary: Add your description here
Author-email: mseep <support@skydeck.ai>
Requires-Python: >=3.12
License-File: LICENSE
Requires-Dist: baostock>=0.8.9
Requires-Dist: httpx>=0.28.1
Requires-Dist: mcp[cli]>=1.2.0
Requires-Dist: pandas>=2.2.3
Requires-Dist: annotated-types>=0.7.0
Requires-Dist: anyio>=4.9.0
Requires-Dist: certifi>=2025.4.26
Requires-Dist: click>=8.1.8
Requires-Dist: colorama>=0.4.6
Requires-Dist: h11>=0.16.0
Requires-Dist: httpcore>=1.0.9
Requires-Dist: httpx-sse>=0.4.0
Requires-Dist: idna>=3.10
Requires-Dist: markdown-it-py>=3.0.0
Requires-Dist: mdurl>=0.1.2
Requires-Dist: numpy>=2.2.5
Requires-Dist: pydantic>=2.11.3
Requires-Dist: pydantic-core>=2.33.1
Requires-Dist: pydantic-settings>=2.9.1
Requires-Dist: pygments>=2.19.1
Requires-Dist: python-dateutil>=2.9.0
Requires-Dist: python-dotenv>=1.1.0
Requires-Dist: pytz>=2025.2
Requires-Dist: rich>=14.0.0
Requires-Dist: shellingham>=1.5.4
Requires-Dist: six>=1.17.0
Requires-Dist: sniffio>=1.3.1
Requires-Dist: sse-starlette>=2.3.3
Requires-Dist: starlette>=0.46.2
Requires-Dist: tabulate>=0.9.0
Requires-Dist: typer>=0.15.3
Requires-Dist: typing-extensions>=4.13.2
Requires-Dist: typing-inspection>=0.4.0
Requires-Dist: tzdata>=2025.2
Requires-Dist: uvicorn>=0.34.2
Dynamic: license-file
